<annotation><folder>dataset/labels/</folder><filename>..\img002.jpg</filename><path>dataset/labels/..\img002.jpg</path><size><width>1280</width><height>853</height><depth>3</depth></size><object><name>kondensator</name><pose>Unspecified</pose><truncated>0</truncated><difficult>0</difficult><bndbox><xmin>203</xmin><ymin>104</ymin><xmax>347</xmax><ymax>204</ymax></bndbox></object><object><name>kondensator</name><pose>Unspecified</pose><truncated>0</truncated><difficult>0</difficult><bndbox><xmin>200</xmin><ymin>217</ymin><xmax>358</xmax><ymax>325</ymax></bndbox></object><object><name>kondensator</name><pose>Unspecified</pose><truncated>0</truncated><difficult>0</difficult><bndbox><xmin>213</xmin><ymin>362</ymin><xmax>339</xmax><ymax>423</ymax></bndbox></object><object><name>kondensator</name><pose>Unspecified</pose><truncated>0</truncated><difficult>0</difficult><bndbox><xmin>176</xmin><ymin>522</ymin><xmax>219</xmax><ymax>616</ymax></bndbox></object><object><name>kondensator</name><pose>Unspecified</pose><truncated>0</truncated><difficult>0</difficult><bndbox><xmin>518</xmin><ymin>511</ymin><xmax>572</xmax><ymax>610</ymax></bndbox></object><object><name>kondensator</name><pose>Unspecified</pose><truncated>0</truncated><difficult>0</difficult><bndbox><xmin>1139</xmin><ymin>511</ymin><xmax>1203</xmax><ymax>625</ymax></bndbox></object><object><name>kondensator</name><pose>Unspecified</pose><truncated>0</truncated><difficult>0</difficult><bndbox><xmin>1118</xmin><ymin>319</ymin><xmax>1162</xmax><ymax>410</ymax></bndbox></object></annotation>