<annotation>
	<folder>cały_dataset</folder>
	<filename>IMG_3710.jpg</filename>
	<path>C:\Users\Karolina\Desktop\cały_dataset\IMG_3710.jpg</path>
	<source>
		<database>Unknown</database>
	</source>
	<size>
		<width>2513</width>
		<height>3410</height>
		<depth>3</depth>
	</size>
	<segmented>0</segmented>
	<object>
		<name>connector</name>
		<pose>Unspecified</pose>
		<truncated>0</truncated>
		<difficult>0</difficult>
		<bndbox>
			<xmin>1188</xmin>
			<ymin>179</ymin>
			<xmax>1292</xmax>
			<ymax>427</ymax>
		</bndbox>
	</object>
	<object>
		<name>connector</name>
		<pose>Unspecified</pose>
		<truncated>0</truncated>
		<difficult>0</difficult>
		<bndbox>
			<xmin>16</xmin>
			<ymin>1355</ymin>
			<xmax>240</xmax>
			<ymax>2191</ymax>
		</bndbox>
	</object>
	<object>
		<name>connector</name>
		<pose>Unspecified</pose>
		<truncated>0</truncated>
		<difficult>0</difficult>
		<bndbox>
			<xmin>8</xmin>
			<ymin>2211</ymin>
			<xmax>248</xmax>
			<ymax>3195</ymax>
		</bndbox>
	</object>
	<object>
		<name>connector</name>
		<pose>Unspecified</pose>
		<truncated>0</truncated>
		<difficult>0</difficult>
		<bndbox>
			<xmin>848</xmin>
			<ymin>1307</ymin>
			<xmax>1152</xmax>
			<ymax>1507</ymax>
		</bndbox>
	</object>
	<object>
		<name>connector</name>
		<pose>Unspecified</pose>
		<truncated>0</truncated>
		<difficult>0</difficult>
		<bndbox>
			<xmin>1604</xmin>
			<ymin>171</ymin>
			<xmax>1812</xmax>
			<ymax>723</ymax>
		</bndbox>
	</object>
	<object>
		<name>connector</name>
		<pose>Unspecified</pose>
		<truncated>0</truncated>
		<difficult>0</difficult>
		<bndbox>
			<xmin>1812</xmin>
			<ymin>171</ymin>
			<xmax>2004</xmax>
			<ymax>731</ymax>
		</bndbox>
	</object>
	<object>
		<name>connector</name>
		<pose>Unspecified</pose>
		<truncated>0</truncated>
		<difficult>0</difficult>
		<bndbox>
			<xmin>2244</xmin>
			<ymin>471</ymin>
			<xmax>2432</xmax>
			<ymax>2431</ymax>
		</bndbox>
	</object>
	<object>
		<name>connector</name>
		<pose>Unspecified</pose>
		<truncated>0</truncated>
		<difficult>0</difficult>
		<bndbox>
			<xmin>1880</xmin>
			<ymin>1379</ymin>
			<xmax>2032</xmax>
			<ymax>2027</ymax>
		</bndbox>
	</object>
	<object>
		<name>connector</name>
		<pose>Unspecified</pose>
		<truncated>0</truncated>
		<difficult>0</difficult>
		<bndbox>
			<xmin>1860</xmin>
			<ymin>2067</ymin>
			<xmax>2016</xmax>
			<ymax>2915</ymax>
		</bndbox>
	</object>
	<object>
		<name>connector</name>
		<pose>Unspecified</pose>
		<truncated>0</truncated>
		<difficult>0</difficult>
		<bndbox>
			<xmin>1196</xmin>
			<ymin>823</ymin>
			<xmax>1424</xmax>
			<ymax>911</ymax>
		</bndbox>
	</object>
	<object>
		<name>connector</name>
		<pose>Unspecified</pose>
		<truncated>0</truncated>
		<difficult>0</difficult>
		<bndbox>
			<xmin>1204</xmin>
			<ymin>1115</ymin>
			<xmax>1400</xmax>
			<ymax>1247</ymax>
		</bndbox>
	</object>
</annotation>
