<annotation><folder /><filename>0ec02dba-80.jpg</filename><path>dataset/inductor-jpg/0ec02dba-80.jpg</path><size><width>4189</width><height>2547</height><depth>3</depth></size><object><name>Induktor</name><pose>Unspecified</pose><truncated>0</truncated><difficult>0</difficult><bndbox><xmin>874</xmin><ymin>1926</ymin><xmax>1096</xmax><ymax>2133</ymax></bndbox></object><object><name>Induktor</name><pose>Unspecified</pose><truncated>0</truncated><difficult>0</difficult><bndbox><xmin>2525</xmin><ymin>1932</ymin><xmax>2741</xmax><ymax>2133</ymax></bndbox></object><object><name>Induktor</name><pose>Unspecified</pose><truncated>0</truncated><difficult>0</difficult><bndbox><xmin>2584</xmin><ymin>1594</ymin><xmax>2785</xmax><ymax>1801</ymax></bndbox></object><object><name>Induktor</name><pose>Unspecified</pose><truncated>0</truncated><difficult>0</difficult><bndbox><xmin>3151</xmin><ymin>1810</ymin><xmax>3355</xmax><ymax>2014</ymax></bndbox></object></annotation>