<annotation><folder>dataset/labels-ic/</folder><filename>..\IMG_3668.jpg</filename><path>dataset/labels-ic/..\IMG_3668.jpg</path><size><width>4284</width><height>5712</height><depth>3</depth></size><object><name>ic</name><pose>Unspecified</pose><truncated>0</truncated><difficult>0</difficult><bndbox><xmin>1792</xmin><ymin>2641</ymin><xmax>1939</xmax><ymax>2783</ymax></bndbox></object><object><name>ic</name><pose>Unspecified</pose><truncated>0</truncated><difficult>0</difficult><bndbox><xmin>1624</xmin><ymin>3088</ymin><xmax>1736</xmax><ymax>3241</ymax></bndbox></object><object><name>ic</name><pose>Unspecified</pose><truncated>0</truncated><difficult>0</difficult><bndbox><xmin>2089</xmin><ymin>3110</ymin><xmax>2471</xmax><ymax>3346</ymax></bndbox></object></annotation>