<annotation><folder>dataset/labels/</folder><filename>..\IMG_3663.jpg</filename><path>dataset/labels/..\IMG_3663.jpg</path><size><width>4284</width><height>5712</height><depth>3</depth></size><object><name>kondensator</name><pose>Unspecified</pose><truncated>0</truncated><difficult>0</difficult><bndbox><xmin>1471</xmin><ymin>1897</ymin><xmax>1507</xmax><ymax>1932</ymax></bndbox></object><object><name>kondensator</name><pose>Unspecified</pose><truncated>0</truncated><difficult>0</difficult><bndbox><xmin>1145</xmin><ymin>2085</ymin><xmax>1201</xmax><ymax>2139</ymax></bndbox></object><object><name>kondensator</name><pose>Unspecified</pose><truncated>0</truncated><difficult>0</difficult><bndbox><xmin>1077</xmin><ymin>2137</ymin><xmax>1127</xmax><ymax>2189</ymax></bndbox></object><object><name>kondensator</name><pose>Unspecified</pose><truncated>0</truncated><difficult>0</difficult><bndbox><xmin>1049</xmin><ymin>2158</ymin><xmax>1103</xmax><ymax>2212</ymax></bndbox></object><object><name>kondensator</name><pose>Unspecified</pose><truncated>0</truncated><difficult>0</difficult><bndbox><xmin>936</xmin><ymin>2209</ymin><xmax>1028</xmax><ymax>2300</ymax></bndbox></object><object><name>kondensator</name><pose>Unspecified</pose><truncated>0</truncated><difficult>0</difficult><bndbox><xmin>969</xmin><ymin>2560</ymin><xmax>1060</xmax><ymax>2648</ymax></bndbox></object><object><name>kondensator</name><pose>Unspecified</pose><truncated>0</truncated><difficult>0</difficult><bndbox><xmin>1094</xmin><ymin>2481</ymin><xmax>1185</xmax><ymax>2572</ymax></bndbox></object><object><name>kondensator</name><pose>Unspecified</pose><truncated>0</truncated><difficult>0</difficult><bndbox><xmin>1244</xmin><ymin>2536</ymin><xmax>1293</xmax><ymax>2581</ymax></bndbox></object><object><name>kondensator</name><pose>Unspecified</pose><truncated>0</truncated><difficult>0</difficult><bndbox><xmin>1320</xmin><ymin>2477</ymin><xmax>1368</xmax><ymax>2526</ymax></bndbox></object><object><name>kondensator</name><pose>Unspecified</pose><truncated>0</truncated><difficult>0</difficult><bndbox><xmin>1345</xmin><ymin>2453</ymin><xmax>1396</xmax><ymax>2503</ymax></bndbox></object><object><name>kondensator</name><pose>Unspecified</pose><truncated>0</truncated><difficult>0</difficult><bndbox><xmin>1448</xmin><ymin>2411</ymin><xmax>1540</xmax><ymax>2497</ymax></bndbox></object><object><name>kondensator</name><pose>Unspecified</pose><truncated>0</truncated><difficult>0</difficult><bndbox><xmin>1402</xmin><ymin>2361</ymin><xmax>1496</xmax><ymax>2450</ymax></bndbox></object><object><name>kondensator</name><pose>Unspecified</pose><truncated>0</truncated><difficult>0</difficult><bndbox><xmin>1920</xmin><ymin>3469</ymin><xmax>2009</xmax><ymax>3561</ymax></bndbox></object><object><name>kondensator</name><pose>Unspecified</pose><truncated>0</truncated><difficult>0</difficult><bndbox><xmin>1975</xmin><ymin>3373</ymin><xmax>2066</xmax><ymax>3461</ymax></bndbox></object><object><name>kondensator</name><pose>Unspecified</pose><truncated>0</truncated><difficult>0</difficult><bndbox><xmin>2153</xmin><ymin>3260</ymin><xmax>2181</xmax><ymax>3289</ymax></bndbox></object><object><name>kondensator</name><pose>Unspecified</pose><truncated>0</truncated><difficult>0</difficult><bndbox><xmin>2077</xmin><ymin>3173</ymin><xmax>2107</xmax><ymax>3204</ymax></bndbox></object><object><name>kondensator</name><pose>Unspecified</pose><truncated>0</truncated><difficult>0</difficult><bndbox><xmin>2380</xmin><ymin>3372</ymin><xmax>2470</xmax><ymax>3465</ymax></bndbox></object><object><name>kondensator</name><pose>Unspecified</pose><truncated>0</truncated><difficult>0</difficult><bndbox><xmin>2239</xmin><ymin>3081</ymin><xmax>2267</xmax><ymax>3111</ymax></bndbox></object><object><name>kondensator</name><pose>Unspecified</pose><truncated>0</truncated><difficult>0</difficult><bndbox><xmin>2350</xmin><ymin>2715</ymin><xmax>2440</xmax><ymax>2806</ymax></bndbox></object><object><name>kondensator</name><pose>Unspecified</pose><truncated>0</truncated><difficult>0</difficult><bndbox><xmin>2386</xmin><ymin>2690</ymin><xmax>2416</xmax><ymax>2723</ymax></bndbox></object><object><name>kondensator</name><pose>Unspecified</pose><truncated>0</truncated><difficult>0</difficult><bndbox><xmin>2395</xmin><ymin>2646</ymin><xmax>2431</xmax><ymax>2683</ymax></bndbox></object><object><name>kondensator</name><pose>Unspecified</pose><truncated>0</truncated><difficult>0</difficult><bndbox><xmin>2424</xmin><ymin>2616</ymin><xmax>2471</xmax><ymax>2666</ymax></bndbox></object><object><name>kondensator</name><pose>Unspecified</pose><truncated>0</truncated><difficult>0</difficult><bndbox><xmin>2342</xmin><ymin>2561</ymin><xmax>2376</xmax><ymax>2596</ymax></bndbox></object><object><name>kondensator</name><pose>Unspecified</pose><truncated>0</truncated><difficult>0</difficult><bndbox><xmin>2293</xmin><ymin>2590</ymin><xmax>2329</xmax><ymax>2626</ymax></bndbox></object><object><name>kondensator</name><pose>Unspecified</pose><truncated>0</truncated><difficult>0</difficult><bndbox><xmin>2296</xmin><ymin>2512</ymin><xmax>2329</xmax><ymax>2543</ymax></bndbox></object><object><name>kondensator</name><pose>Unspecified</pose><truncated>0</truncated><difficult>0</difficult><bndbox><xmin>2203</xmin><ymin>2557</ymin><xmax>2232</xmax><ymax>2587</ymax></bndbox></object><object><name>kondensator</name><pose>Unspecified</pose><truncated>0</truncated><difficult>0</difficult><bndbox><xmin>2106</xmin><ymin>2529</ymin><xmax>2136</xmax><ymax>2558</ymax></bndbox></object><object><name>kondensator</name><pose>Unspecified</pose><truncated>0</truncated><difficult>0</difficult><bndbox><xmin>2147</xmin><ymin>2573</ymin><xmax>2174</xmax><ymax>2602</ymax></bndbox></object><object><name>kondensator</name><pose>Unspecified</pose><truncated>0</truncated><difficult>0</difficult><bndbox><xmin>2119</xmin><ymin>2583</ymin><xmax>2148</xmax><ymax>2615</ymax></bndbox></object><object><name>kondensator</name><pose>Unspecified</pose><truncated>0</truncated><difficult>0</difficult><bndbox><xmin>1988</xmin><ymin>2640</ymin><xmax>2019</xmax><ymax>2672</ymax></bndbox></object><object><name>kondensator</name><pose>Unspecified</pose><truncated>0</truncated><difficult>0</difficult><bndbox><xmin>2095</xmin><ymin>2657</ymin><xmax>2128</xmax><ymax>2690</ymax></bndbox></object><object><name>kondensator</name><pose>Unspecified</pose><truncated>0</truncated><difficult>0</difficult><bndbox><xmin>2025</xmin><ymin>2678</ymin><xmax>2056</xmax><ymax>2711</ymax></bndbox></object><object><name>kondensator</name><pose>Unspecified</pose><truncated>0</truncated><difficult>0</difficult><bndbox><xmin>2122</xmin><ymin>2706</ymin><xmax>2149</xmax><ymax>2734</ymax></bndbox></object><object><name>kondensator</name><pose>Unspecified</pose><truncated>0</truncated><difficult>0</difficult><bndbox><xmin>2096</xmin><ymin>2778</ymin><xmax>2127</xmax><ymax>2796</ymax></bndbox></object><object><name>kondensator</name><pose>Unspecified</pose><truncated>0</truncated><difficult>0</difficult><bndbox><xmin>2131</xmin><ymin>2803</ymin><xmax>2160</xmax><ymax>2835</ymax></bndbox></object><object><name>kondensator</name><pose>Unspecified</pose><truncated>0</truncated><difficult>0</difficult><bndbox><xmin>2173</xmin><ymin>2842</ymin><xmax>2202</xmax><ymax>2874</ymax></bndbox></object><object><name>kondensator</name><pose>Unspecified</pose><truncated>0</truncated><difficult>0</difficult><bndbox><xmin>2228</xmin><ymin>2811</ymin><xmax>2261</xmax><ymax>2844</ymax></bndbox></object><object><name>kondensator</name><pose>Unspecified</pose><truncated>0</truncated><difficult>0</difficult><bndbox><xmin>2289</xmin><ymin>2761</ymin><xmax>2318</xmax><ymax>2792</ymax></bndbox></object><object><name>kondensator</name><pose>Unspecified</pose><truncated>0</truncated><difficult>0</difficult><bndbox><xmin>2276</xmin><ymin>2717</ymin><xmax>2307</xmax><ymax>2750</ymax></bndbox></object><object><name>kondensator</name><pose>Unspecified</pose><truncated>0</truncated><difficult>0</difficult><bndbox><xmin>2695</xmin><ymin>3002</ymin><xmax>2792</xmax><ymax>3096</ymax></bndbox></object><object><name>kondensator</name><pose>Unspecified</pose><truncated>0</truncated><difficult>0</difficult><bndbox><xmin>2893</xmin><ymin>2851</ymin><xmax>2999</xmax><ymax>2952</ymax></bndbox></object></annotation>